README
setup.cfg
setup.py
beaker_extensions/__init__.py
beaker_extensions/dynomite_.py
beaker_extensions/nosql.py
beaker_extensions/pytyrant.py
beaker_extensions/redis_.py
beaker_extensions/riak.py
beaker_extensions/ringo.py
beaker_extensions/ringogw.py
beaker_extensions/tyrant_.py
beaker_extensions.egg-info/PKG-INFO
beaker_extensions.egg-info/SOURCES.txt
beaker_extensions.egg-info/dependency_links.txt
beaker_extensions.egg-info/entry_points.txt
beaker_extensions.egg-info/not-zip-safe
beaker_extensions.egg-info/top_level.txt