Metadata-Version: 1.0
Name: beaker-extensions
Version: 0.1.1dev
Summary: Beaker extensions for additional back-end stores.
Home-page: UNKNOWN
Author: Didip Kerabat
Author-email: didipk@gmail.com
License: UNKNOWN
Platform: UNKNOWN
